testing_package_exedoc/__init__.py
testing_package_exedoc/exedoc.py
testing_package_exedoc-0.0.9.dist-info/LICENSE
testing_package_exedoc-0.0.9.dist-info/METADATA
testing_package_exedoc-0.0.9.dist-info/WHEEL
testing_package_exedoc-0.0.9.dist-info/top_level.txt
testing_package_exedoc-0.0.9.dist-info/RECORD
