Metadata-Version: 2.1
Name: testing_package_exedoc
Version: 0.0.9
Summary: A small package for testing exedoc
Author-email: Rompni <andresnavarrodev@gmail.com>
Project-URL: Homepage, https://github.com/pypa/sampleproject
Project-URL: Issues, https://github.com/pypa/sampleproject/issues
Classifier: Programming Language :: Python :: 3
Classifier: Operating System :: OS Independent
Requires-Python: >=3.9
License-File: LICENSE
